fastapi_template/__init__.py
aa_fastapi_template-0.25.0.dist-info/LICENSE
aa_fastapi_template-0.25.0.dist-info/METADATA
aa_fastapi_template-0.25.0.dist-info/WHEEL
aa_fastapi_template-0.25.0.dist-info/top_level.txt
aa_fastapi_template-0.25.0.dist-info/RECORD
