Metadata-Version: 2.1
Name: aa-fastapi-template
Version: 0.25.0
Summary: A robust and sensible baseline for kick-starting any new FastAPI application.
Author-email: Aaron Imbrock <aaron@sizza.net>
Maintainer-email: Aaron Imbrock <aaron@sizza.net>
License: Copyright Aaron Imbrock 2024
Project-URL: Documentation, https://github.com/aaron-imbrock/aa-fastapi-template
Project-URL: Homepage, https://pypi.org/project/aa-fastapi-template/
Project-URL: Issues, https://github.com/aaron-imbrock/aa-fastapi-template/issues
Project-URL: Repository, https://github.com/aaron-imbrock/aa-fastapi-template
Keywords: fastapi
Classifier: Intended Audience :: Developers
Classifier: License :: OSI Approved :: MIT License
Classifier: Natural Language :: English
Classifier: Development Status :: 4 - Beta
Classifier: Programming Language :: Python :: 3
Classifier: Programming Language :: Python :: 3.10
Classifier: Programming Language :: Python :: 3.11
Classifier: Programming Language :: Python :: 3.12
Classifier: Framework :: FastAPI
Requires-Python: >=3.10
License-File: LICENSE
Requires-Dist: asyncpg ==0.29.0
Requires-Dist: environs ==10.3.0
Requires-Dist: fastapi ==0.110.0
Requires-Dist: mypy ==1.9.0
Requires-Dist: psycopg2-binary ==2.9.9
Requires-Dist: pydantic ==2.6.2
Requires-Dist: python-dotenv ==1.0.1
Requires-Dist: sqlalchemy ==2.0.27
Requires-Dist: sqlmodel ==0.0.16
Requires-Dist: uvicorn ==0.27.1
Provides-Extra: build
Requires-Dist: setuptools ; extra == 'build'
Requires-Dist: build ; extra == 'build'
Requires-Dist: twine ; extra == 'build'
Provides-Extra: dev
Requires-Dist: aa-fastapi-template[tests] ; extra == 'dev'
Requires-Dist: black ==24.2.0 ; extra == 'dev'
Requires-Dist: httpx ==0.27.0 ; extra == 'dev'
Requires-Dist: isort ==5.13.2 ; extra == 'dev'
Requires-Dist: ruff ==0.4.1 ; extra == 'dev'
Requires-Dist: toml ==0.10.2 ; extra == 'dev'
Requires-Dist: types-toml ==0.10.8.7 ; extra == 'dev'
Provides-Extra: tests
Requires-Dist: pytest ==8.1.1 ; extra == 'tests'
Requires-Dist: pytest-mock ==3.14.0 ; extra == 'tests'
Requires-Dist: hypothesis ==6.98.11 ; extra == 'tests'
Requires-Dist: pytest-cov ==5.0.0 ; extra == 'tests'
Requires-Dist: pytest-xdist ==3.6.0 ; extra == 'tests'
Requires-Dist: pytest-md ==0.2.0 ; extra == 'tests'
Requires-Dist: pytest-emoji ==0.2.0 ; extra == 'tests'
Requires-Dist: tox ==4.13.0 ; extra == 'tests'
